money/__init__.py
money/currency.py
money/exceptions.py
money/money.py
py_money-0.5.0.dist-info/LICENSE.txt
py_money-0.5.0.dist-info/METADATA
py_money-0.5.0.dist-info/WHEEL
py_money-0.5.0.dist-info/top_level.txt
py_money-0.5.0.dist-info/RECORD
