Metadata-Version: 1.1
Name: py-money
Version: 0.5.0
Summary: Money module for python
Home-page: https://github.com/vimeo/py-money
Author: J.C. Manzo
Author-email: jnmanzo@gmail.com
License: MIT
Keywords: money currency
Platform: UNKNOWN
Classifier: Development Status :: 4 - Beta
Classifier: Intended Audience :: Developers
Classifier: License :: OSI Approved :: MIT License
Classifier: Programming Language :: Python :: 3
